{
  "name": "Account",
  "base": "PersistedModel",
  "idInjection": false,
  "options": {
    "validateUpsert": true
  },
  "properties": {
    "id": {
      "type": "string",
      "id": true,
      "required": true,
      "defaultFn": "uuidv4"
    },
    "alias": {
      "type": "string",
      "required": true
    },
    "name": {
      "type": "string",
      "required": true
    },
    "config": {
      "type": "object",
      "required": true
    }
  },
  "validations": [],
  "relations": {
    "appUsers": {
      "type": "hasMany",
      "model": "AppUser",
      "foreignKey": "accountId",
      "through": "AccountUser"
    }
  },
  "acls": [],
  "methods": {}
}