{
  "name": "Transaction",
  "base": "PersistedModel",
  "idInjection": true,
  "options": {
    "validateUpsert": true
  },
  "properties": {
    "date": {
      "type": "string",
      "required": true
    },
    "description": {
      "type": "string"
    },
    "amount": {
      "type": "number",
      "required": true
    },
    "file": {
      "type": "string"
    }
  },
  "validations": [],
  "relations": {
    "company": {
      "type": "belongsTo",
      "model": "Company",
      "foreignKey": ""
    }
  },
  "acls": [],
  "methods": {}
}
