{
  "alias": "demo",
  "name": "Demo Company",
  "secret": null,
  "user": null,
  "database": {
    "prefix": "demo",
    "host": "http://s2.cgeosoft.com:5984",
    "user": "demo",
    "pass": "demo"
  },
  "modules": {
    "@blnc/core-common": {
      "enabled": true
    },
    "@blnc/core-dashboard": {
      "enabled": true
    },
    "@blnc/core-profiles": {
      "enabled": true
    },
    "@blnc/core-settings": {
      "enabled": true
    },
    "@blnc/business-contacts": {
      "enabled": true
    },
    "@blnc/business-orders": {
      "enabled": true
    },
    "@blnc/business-invoices": {
      "enabled": true
    },
    "@blnc/marketing-presentations": {
      "enabled": true
    },
    "@blnc/teams-projects": {
      "enabled": true
    },
    "@blnc/teams-chat": {
      "enabled": true
    },
    "@blnc/reports": {
      "enabled": true
    }
  },
  "params": null
}
